lsst/__init__.py
lsst/resources/__init__.py
lsst/resources/_resourcePath.py
lsst/resources/dav.py
lsst/resources/davutils.py
lsst/resources/eups.py
lsst/resources/file.py
lsst/resources/gs.py
lsst/resources/http.py
lsst/resources/location.py
lsst/resources/mem.py
lsst/resources/packageresource.py
lsst/resources/proxied.py
lsst/resources/py.typed
lsst/resources/s3.py
lsst/resources/s3utils.py
lsst/resources/schemeless.py
lsst/resources/tests.py
lsst/resources/utils.py
lsst/resources/version.py
lsst/resources/_resourceHandles/__init__.py
lsst/resources/_resourceHandles/_baseResourceHandle.py
lsst/resources/_resourceHandles/_davResourceHandle.py
lsst/resources/_resourceHandles/_fileResourceHandle.py
lsst/resources/_resourceHandles/_httpResourceHandle.py
lsst/resources/_resourceHandles/_s3ResourceHandle.py
lsst_resources-30.2026.300.dist-info/licenses/COPYRIGHT
lsst_resources-30.2026.300.dist-info/licenses/LICENSE
lsst_resources-30.2026.300.dist-info/METADATA
lsst_resources-30.2026.300.dist-info/WHEEL
lsst_resources-30.2026.300.dist-info/top_level.txt
lsst_resources-30.2026.300.dist-info/zip-safe
lsst_resources-30.2026.300.dist-info/RECORD
