Metadata-Version: 2.4
Name: lsst-resources
Version: 30.2026.300
Summary: An abstraction layer for reading and writing from URI file resources.
Author-email: Rubin Observatory Data Management <dm-admin@lists.lsst.org>
License-Expression: BSD-3-Clause
Project-URL: Homepage, https://github.com/lsst/resources
Keywords: lsst
Classifier: Intended Audience :: Developers
Classifier: Operating System :: OS Independent
Classifier: Programming Language :: Python :: 3
Classifier: Programming Language :: Python :: 3.11
Classifier: Programming Language :: Python :: 3.12
Classifier: Programming Language :: Python :: 3.13
Requires-Python: >=3.11.0
License-File: COPYRIGHT
License-File: LICENSE
Requires-Dist: lsst-utils
Provides-Extra: s3
Requires-Dist: boto3>=1.13; extra == "s3"
Requires-Dist: backoff>=1.10; extra == "s3"
Provides-Extra: https
Requires-Dist: astropy>=4.0; extra == "https"
Requires-Dist: requests>=2.26.0; extra == "https"
Requires-Dist: urllib3>=1.25.10; extra == "https"
Requires-Dist: defusedxml; extra == "https"
Provides-Extra: gs
Requires-Dist: google-cloud-storage; extra == "gs"
Provides-Extra: test
Requires-Dist: moto!=5.0.0,>=1.3; extra == "test"
Requires-Dist: pytest>=3.2; extra == "test"
Requires-Dist: responses>=0.12.0; extra == "test"
Dynamic: license-file
